{
  "frame_id": 10,
  "frame_path": "data\\frames\\video_1\\frame_000009_1499ms.jpg",
  "ocr_version": "PP-OCRv5",
  "processing_time": 0.771,
  "raw_result": [
    {
      "img": {
        "ocr_res_img": "<PIL.Image.Image image mode=RGB size=1152x1280 at 0x15E81DC7290>",
        "preprocessed_img": "<PIL.Image.Image image mode=RGB size=1728x1305 at 0x15E81DC6DD0>"
      },
      "json": {
        "res": {
          "input_path": "data\\frames\\video_1\\frame_000009_1499ms.jpg",
          "page_index": null,
          "model_settings": {
            "use_doc_preprocessor": true,
            "use_textline_orientation": true
          },
          "doc_preprocessor_res": {
            "input_path": null,
            "page_index": null,
            "model_settings": {
              "use_doc_orientation_classify": true,
              "use_doc_unwarping": true
            },
            "angle": 0
          },
          "dt_polys": [
            [
              [
                70,
                42
              ],
              [
                227,
                42
              ],
              [
                227,
                96
              ],
              [
                70,
                96
              ]
            ],
            [
              [
                98,
                134
              ],
              [
                536,
                147
              ],
              [
                535,
                184
              ],
              [
                97,
                171
              ]
            ],
            [
              [
                96,
                175
              ],
              [
                553,
                188
              ],
              [
                552,
                223
              ],
              [
                95,
                210
              ]
            ],
            [
              [
                97,
                246
              ],
              [
                374,
                258
              ],
              [
                373,
                293
              ],
              [
                96,
                281
              ]
            ],
            [
              [
                477,
                259
              ],
              [
                562,
                257
              ],
              [
                563,
                290
              ],
              [
                478,
                292
              ]
            ],
            [
              [
                97,
                287
              ],
              [
                435,
                298
              ],
              [
                434,
                328
              ],
              [
                96,
                317
              ]
            ],
            [
              [
                97,
                358
              ],
              [
                464,
                360
              ],
              [
                464,
                395
              ],
              [
                97,
                393
              ]
            ],
            [
              [
                492,
                362
              ],
              [
                566,
                362
              ],
              [
                566,
                391
              ],
              [
                492,
                391
              ]
            ],
            [
              [
                99,
                397
              ],
              [
                559,
                397
              ],
              [
                559,
                427
              ],
              [
                99,
                427
              ]
            ],
            [
              [
                96,
                467
              ],
              [
                244,
                462
              ],
              [
                245,
                498
              ],
              [
                97,
                503
              ]
            ],
            [
              [
                492,
                466
              ],
              [
                569,
                466
              ],
              [
                569,
                499
              ],
              [
                492,
                499
              ]
            ],
            [
              [
                12,
                484
              ],
              [
                65,
                484
              ],
              [
                65,
                519
              ],
              [
                12,
                519
              ]
            ],
            [
              [
                99,
                503
              ],
              [
                194,
                503
              ],
              [
                194,
                535
              ],
              [
                99,
                535
              ]
            ],
            [
              [
                10,
                580
              ],
              [
                69,
                580
              ],
              [
                69,
                614
              ],
              [
                10,
                614
              ]
            ],
            [
              [
                99,
                574
              ],
              [
                415,
                572
              ],
              [
                415,
                603
              ],
              [
                99,
                605
              ]
            ],
            [
              [
                439,
                572
              ],
              [
                494,
                572
              ],
              [
                494,
                602
              ],
              [
                439,
                602
              ]
            ],
            [
              [
                510,
                571
              ],
              [
                569,
                573
              ],
              [
                568,
                607
              ],
              [
                509,
                605
              ]
            ],
            [
              [
                11,
                607
              ],
              [
                69,
                607
              ],
              [
                69,
                641
              ],
              [
                11,
                641
              ]
            ],
            [
              [
                100,
                612
              ],
              [
                341,
                609
              ],
              [
                341,
                637
              ],
              [
                100,
                640
              ]
            ],
            [
              [
                93,
                679
              ],
              [
                191,
                677
              ],
              [
                192,
                713
              ],
              [
                94,
                715
              ]
            ],
            [
              [
                513,
                679
              ],
              [
                570,
                679
              ],
              [
                570,
                710
              ],
              [
                513,
                710
              ]
            ],
            [
              [
                98,
                719
              ],
              [
                557,
                714
              ],
              [
                557,
                741
              ],
              [
                98,
                746
              ]
            ],
            [
              [
                96,
                785
              ],
              [
                244,
                782
              ],
              [
                245,
                817
              ],
              [
                97,
                820
              ]
            ],
            [
              [
                512,
                781
              ],
              [
                572,
                779
              ],
              [
                573,
                814
              ],
              [
                513,
                816
              ]
            ],
            [
              [
                104,
                822
              ],
              [
                257,
                822
              ],
              [
                257,
                853
              ],
              [
                104,
                853
              ]
            ],
            [
              [
                9,
                893
              ],
              [
                63,
                890
              ],
              [
                67,
                959
              ],
              [
                13,
                962
              ]
            ],
            [
              [
                96,
                894
              ],
              [
                409,
                890
              ],
              [
                409,
                924
              ],
              [
                96,
                928
              ]
            ],
            [
              [
                443,
                889
              ],
              [
                500,
                889
              ],
              [
                500,
                920
              ],
              [
                443,
                920
              ]
            ],
            [
              [
                515,
                890
              ],
              [
                573,
                890
              ],
              [
                573,
                921
              ],
              [
                515,
                921
              ]
            ],
            [
              [
                97,
                933
              ],
              [
                566,
                927
              ],
              [
                566,
                955
              ],
              [
                97,
                961
              ]
            ],
            [
              [
                96,
                1003
              ],
              [
                348,
                998
              ],
              [
                348,
                1032
              ],
              [
                96,
                1037
              ]
            ],
            [
              [
                514,
                998
              ],
              [
                574,
                998
              ],
              [
                574,
                1033
              ],
              [
                514,
                1033
              ]
            ],
            [
              [
                95,
                1041
              ],
              [
                200,
                1039
              ],
              [
                201,
                1071
              ],
              [
                96,
                1073
              ]
            ],
            [
              [
                97,
                1112
              ],
              [
                320,
                1107
              ],
              [
                321,
                1141
              ],
              [
                98,
                1146
              ]
            ],
            [
              [
                471,
                1110
              ],
              [
                572,
                1112
              ],
              [
                571,
                1145
              ],
              [
                470,
                1143
              ]
            ],
            [
              [
                97,
                1149
              ],
              [
                225,
                1147
              ],
              [
                225,
                1178
              ],
              [
                97,
                1180
              ]
            ],
            [
              [
                528,
                1222
              ],
              [
                568,
                1222
              ],
              [
                568,
                1240
              ],
              [
                528,
                1240
              ]
            ],
            [
              [
                526,
                1238
              ],
              [
                569,
                1238
              ],
              [
                569,
                1261
              ],
              [
                526,
                1261
              ]
            ],
            [
              [
                208,
                1265
              ],
              [
                252,
                1265
              ],
              [
                252,
                1280
              ],
              [
                208,
                1280
              ]
            ],
            [
              [
                292,
                1267
              ],
              [
                376,
                1267
              ],
              [
                376,
                1280
              ],
              [
                292,
                1280
              ]
            ],
            [
              [
                399,
                1271
              ],
              [
                442,
                1271
              ],
              [
                442,
                1278
              ],
              [
                399,
                1278
              ]
            ]
          ],
          "text_det_params": {
            "limit_side_len": 64,
            "limit_type": "min",
            "thresh": 0.3,
            "max_side_limit": 4000,
            "box_thresh": 0.6,
            "unclip_ratio": 1.5
          },
          "text_type": "general",
          "textline_orientation_angles": [
            0,
            0,
            0,
            0,
            0,
            0,
            0,
            0,
            0,
            0,
            0,
            0,
            0,
            0,
            0,
            0,
            0,
            0,
            0,
            0,
            0,
            0,
            0,
            0,
            0,
            0,
            0,
            0,
            0,
            0,
            0,
            0,
            0,
            0,
            0,
            0,
            0,
            0,
            0,
            0,
            0
          ],
          "text_rec_score_thresh": 0.0,
          "rec_texts": [
            "加载中..",
            "飞书技术训练营（测试开发）-第二…",
            "明天16:00-17:00|F37-10[应急会议…",
            "你的专属提效工具推荐",
            "4月7日",
            "来看看为你量身定制的效率工具",
            "培训2-耗时指标如何测试外部",
            "09:57",
            "吕鑫：识别的是一个过程(阶段)，这个过…",
            "张思宇外部",
            "09:45",
            "HU",
            "okok",
            "飞书",
            "飞书技术训练营-测试开…",
            "外部",
            "昨天",
            "技术",
            "肖凯琴：后续课程预告：",
            "17外部",
            "昨天",
            "杨鸿博：我都可以，大哥们剩哪个给我我…",
            "王方舟外部",
            "昨天",
            "好的，谢谢",
            "17",
            "17-Bug消灭队-飞书技…",
            "外部",
            "昨天",
            "张思宇-哈尔滨理工大学-计算机科学与技…",
            "视频会议助手机器人",
            "昨天",
            "权限开通",
            "联系人助手机器人",
            "6月24日",
            "联系人申请",
            "用",
            "司",
            "推荐",
            "名维表格",
            ""
          ],
          "rec_scores": [
            0.9662459492683411,
            0.9256483912467957,
            0.8848861455917358,
            0.9984361529350281,
            0.9997424483299255,
            0.994804859161377,
            0.9970985651016235,
            0.9735094904899597,
            0.9593693017959595,
            0.9952219724655151,
            0.9903495907783508,
            0.9933964610099792,
            0.9961077570915222,
            0.99904465675354,
            0.9631913304328918,
            0.9999169707298279,
            0.9995911717414856,
            0.9994105100631714,
            0.985771894454956,
            0.9996404647827148,
            0.999586820602417,
            0.9324201345443726,
            0.9984149932861328,
            0.9996684789657593,
            0.9956797361373901,
            0.6220225691795349,
            0.9542573690414429,
            0.9998945593833923,
            0.9988287091255188,
            0.9653838276863098,
            0.9976715445518494,
            0.9997122287750244,
            0.9998302459716797,
            0.9971709251403809,
            0.9993581771850586,
            0.9994579553604126,
            0.06776627153158188,
            0.549980640411377,
            0.9618321657180786,
            0.8809468746185303,
            0.0
          ],
          "rec_polys": [
            [
              [
                70,
                42
              ],
              [
                227,
                42
              ],
              [
                227,
                96
              ],
              [
                70,
                96
              ]
            ],
            [
              [
                98,
                134
              ],
              [
                536,
                147
              ],
              [
                535,
                184
              ],
              [
                97,
                171
              ]
            ],
            [
              [
                96,
                175
              ],
              [
                553,
                188
              ],
              [
                552,
                223
              ],
              [
                95,
                210
              ]
            ],
            [
              [
                97,
                246
              ],
              [
                374,
                258
              ],
              [
                373,
                293
              ],
              [
                96,
                281
              ]
            ],
            [
              [
                477,
                259
              ],
              [
                562,
                257
              ],
              [
                563,
                290
              ],
              [
                478,
                292
              ]
            ],
            [
              [
                97,
                287
              ],
              [
                435,
                298
              ],
              [
                434,
                328
              ],
              [
                96,
                317
              ]
            ],
            [
              [
                97,
                358
              ],
              [
                464,
                360
              ],
              [
                464,
                395
              ],
              [
                97,
                393
              ]
            ],
            [
              [
                492,
                362
              ],
              [
                566,
                362
              ],
              [
                566,
                391
              ],
              [
                492,
                391
              ]
            ],
            [
              [
                99,
                397
              ],
              [
                559,
                397
              ],
              [
                559,
                427
              ],
              [
                99,
                427
              ]
            ],
            [
              [
                96,
                467
              ],
              [
                244,
                462
              ],
              [
                245,
                498
              ],
              [
                97,
                503
              ]
            ],
            [
              [
                492,
                466
              ],
              [
                569,
                466
              ],
              [
                569,
                499
              ],
              [
                492,
                499
              ]
            ],
            [
              [
                12,
                484
              ],
              [
                65,
                484
              ],
              [
                65,
                519
              ],
              [
                12,
                519
              ]
            ],
            [
              [
                99,
                503
              ],
              [
                194,
                503
              ],
              [
                194,
                535
              ],
              [
                99,
                535
              ]
            ],
            [
              [
                10,
                580
              ],
              [
                69,
                580
              ],
              [
                69,
                614
              ],
              [
                10,
                614
              ]
            ],
            [
              [
                99,
                574
              ],
              [
                415,
                572
              ],
              [
                415,
                603
              ],
              [
                99,
                605
              ]
            ],
            [
              [
                439,
                572
              ],
              [
                494,
                572
              ],
              [
                494,
                602
              ],
              [
                439,
                602
              ]
            ],
            [
              [
                510,
                571
              ],
              [
                569,
                573
              ],
              [
                568,
                607
              ],
              [
                509,
                605
              ]
            ],
            [
              [
                11,
                607
              ],
              [
                69,
                607
              ],
              [
                69,
                641
              ],
              [
                11,
                641
              ]
            ],
            [
              [
                100,
                612
              ],
              [
                341,
                609
              ],
              [
                341,
                637
              ],
              [
                100,
                640
              ]
            ],
            [
              [
                93,
                679
              ],
              [
                191,
                677
              ],
              [
                192,
                713
              ],
              [
                94,
                715
              ]
            ],
            [
              [
                513,
                679
              ],
              [
                570,
                679
              ],
              [
                570,
                710
              ],
              [
                513,
                710
              ]
            ],
            [
              [
                98,
                719
              ],
              [
                557,
                714
              ],
              [
                557,
                741
              ],
              [
                98,
                746
              ]
            ],
            [
              [
                96,
                785
              ],
              [
                244,
                782
              ],
              [
                245,
                817
              ],
              [
                97,
                820
              ]
            ],
            [
              [
                512,
                781
              ],
              [
                572,
                779
              ],
              [
                573,
                814
              ],
              [
                513,
                816
              ]
            ],
            [
              [
                104,
                822
              ],
              [
                257,
                822
              ],
              [
                257,
                853
              ],
              [
                104,
                853
              ]
            ],
            [
              [
                9,
                893
              ],
              [
                63,
                890
              ],
              [
                67,
                959
              ],
              [
                13,
                962
              ]
            ],
            [
              [
                96,
                894
              ],
              [
                409,
                890
              ],
              [
                409,
                924
              ],
              [
                96,
                928
              ]
            ],
            [
              [
                443,
                889
              ],
              [
                500,
                889
              ],
              [
                500,
                920
              ],
              [
                443,
                920
              ]
            ],
            [
              [
                515,
                890
              ],
              [
                573,
                890
              ],
              [
                573,
                921
              ],
              [
                515,
                921
              ]
            ],
            [
              [
                97,
                933
              ],
              [
                566,
                927
              ],
              [
                566,
                955
              ],
              [
                97,
                961
              ]
            ],
            [
              [
                96,
                1003
              ],
              [
                348,
                998
              ],
              [
                348,
                1032
              ],
              [
                96,
                1037
              ]
            ],
            [
              [
                514,
                998
              ],
              [
                574,
                998
              ],
              [
                574,
                1033
              ],
              [
                514,
                1033
              ]
            ],
            [
              [
                95,
                1041
              ],
              [
                200,
                1039
              ],
              [
                201,
                1071
              ],
              [
                96,
                1073
              ]
            ],
            [
              [
                97,
                1112
              ],
              [
                320,
                1107
              ],
              [
                321,
                1141
              ],
              [
                98,
                1146
              ]
            ],
            [
              [
                471,
                1110
              ],
              [
                572,
                1112
              ],
              [
                571,
                1145
              ],
              [
                470,
                1143
              ]
            ],
            [
              [
                97,
                1149
              ],
              [
                225,
                1147
              ],
              [
                225,
                1178
              ],
              [
                97,
                1180
              ]
            ],
            [
              [
                528,
                1222
              ],
              [
                568,
                1222
              ],
              [
                568,
                1240
              ],
              [
                528,
                1240
              ]
            ],
            [
              [
                526,
                1238
              ],
              [
                569,
                1238
              ],
              [
                569,
                1261
              ],
              [
                526,
                1261
              ]
            ],
            [
              [
                208,
                1265
              ],
              [
                252,
                1265
              ],
              [
                252,
                1280
              ],
              [
                208,
                1280
              ]
            ],
            [
              [
                292,
                1267
              ],
              [
                376,
                1267
              ],
              [
                376,
                1280
              ],
              [
                292,
                1280
              ]
            ],
            [
              [
                399,
                1271
              ],
              [
                442,
                1271
              ],
              [
                442,
                1278
              ],
              [
                399,
                1278
              ]
            ]
          ],
          "rec_boxes": [
            [
              70,
              42,
              227,
              96
            ],
            [
              97,
              134,
              536,
              184
            ],
            [
              95,
              175,
              553,
              223
            ],
            [
              96,
              246,
              374,
              293
            ],
            [
              477,
              257,
              563,
              292
            ],
            [
              96,
              287,
              435,
              328
            ],
            [
              97,
              358,
              464,
              395
            ],
            [
              492,
              362,
              566,
              391
            ],
            [
              99,
              397,
              559,
              427
            ],
            [
              96,
              462,
              245,
              503
            ],
            [
              492,
              466,
              569,
              499
            ],
            [
              12,
              484,
              65,
              519
            ],
            [
              99,
              503,
              194,
              535
            ],
            [
              10,
              580,
              69,
              614
            ],
            [
              99,
              572,
              415,
              605
            ],
            [
              439,
              572,
              494,
              602
            ],
            [
              509,
              571,
              569,
              607
            ],
            [
              11,
              607,
              69,
              641
            ],
            [
              100,
              609,
              341,
              640
            ],
            [
              93,
              677,
              192,
              715
            ],
            [
              513,
              679,
              570,
              710
            ],
            [
              98,
              714,
              557,
              746
            ],
            [
              96,
              782,
              245,
              820
            ],
            [
              512,
              779,
              573,
              816
            ],
            [
              104,
              822,
              257,
              853
            ],
            [
              9,
              890,
              67,
              962
            ],
            [
              96,
              890,
              409,
              928
            ],
            [
              443,
              889,
              500,
              920
            ],
            [
              515,
              890,
              573,
              921
            ],
            [
              97,
              927,
              566,
              961
            ],
            [
              96,
              998,
              348,
              1037
            ],
            [
              514,
              998,
              574,
              1033
            ],
            [
              95,
              1039,
              201,
              1073
            ],
            [
              97,
              1107,
              321,
              1146
            ],
            [
              470,
              1110,
              572,
              1145
            ],
            [
              97,
              1147,
              225,
              1180
            ],
            [
              528,
              1222,
              568,
              1240
            ],
            [
              526,
              1238,
              569,
              1261
            ],
            [
              208,
              1265,
              252,
              1280
            ],
            [
              292,
              1267,
              376,
              1280
            ],
            [
              399,
              1271,
              442,
              1278
            ]
          ]
        }
      },
      "str": {
        "res": {
          "input_path": "data\\frames\\video_1\\frame_000009_1499ms.jpg",
          "page_index": null,
          "model_settings": {
            "use_doc_preprocessor": true,
            "use_textline_orientation": true
          },
          "doc_preprocessor_res": {
            "input_path": null,
            "page_index": null,
            "model_settings": {
              "use_doc_orientation_classify": true,
              "use_doc_unwarping": true
            },
            "angle": 0
          },
          "dt_polys": "[[[  70   42]\n  ...\n  [  70   96]]\n\n ...\n\n [[ 399 1271]\n  ...\n  [ 399 1278]]]",
          "text_det_params": {
            "limit_side_len": 64,
            "limit_type": "min",
            "thresh": 0.3,
            "max_side_limit": 4000,
            "box_thresh": 0.6,
            "unclip_ratio": 1.5
          },
          "text_type": "general",
          "textline_orientation_angles": "[0 ... 0]",
          "text_rec_score_thresh": 0.0,
          "rec_texts": [
            "加载中..",
            "飞书技术训练营（测试开发）-第二…",
            "明天16:00-17:00|F37-10[应急会议…",
            "你的专属提效工具推荐",
            "4月7日",
            "来看看为你量身定制的效率工具",
            "培训2-耗时指标如何测试外部",
            "09:57",
            "吕鑫：识别的是一个过程(阶段)，这个过…",
            "张思宇外部",
            "09:45",
            "HU",
            "okok",
            "飞书",
            "飞书技术训练营-测试开…",
            "外部",
            "昨天",
            "技术",
            "肖凯琴：后续课程预告：",
            "17外部",
            "昨天",
            "杨鸿博：我都可以，大哥们剩哪个给我我…",
            "王方舟外部",
            "昨天",
            "好的，谢谢",
            "17",
            "17-Bug消灭队-飞书技…",
            "外部",
            "昨天",
            "张思宇-哈尔滨理工大学-计算机科学与技…",
            "视频会议助手机器人",
            "昨天",
            "权限开通",
            "联系人助手机器人",
            "6月24日",
            "联系人申请",
            "用",
            "司",
            "推荐",
            "名维表格",
            ""
          ],
          "rec_scores": "[0.96624595 ... 0.        ]",
          "rec_polys": "[[[  70   42]\n  ...\n  [  70   96]]\n\n ...\n\n [[ 399 1271]\n  ...\n  [ 399 1278]]]",
          "rec_boxes": "[[  70 ...   96]\n ...\n [ 399 ... 1278]]"
        }
      }
    }
  ]
}